envdrift/__init__.py
envdrift/_version.py
envdrift/api.py
envdrift/cli.py
envdrift/config.py
envdrift/constants.json
envdrift/env_files.py
envdrift/py.typed
envdrift/agent/__init__.py
envdrift/agent/registry.py
envdrift/cli_commands/__init__.py
envdrift/cli_commands/agent.py
envdrift/cli_commands/diff.py
envdrift/cli_commands/encryption.py
envdrift/cli_commands/encryption_helpers.py
envdrift/cli_commands/guard.py
envdrift/cli_commands/hook.py
envdrift/cli_commands/init_cmd.py
envdrift/cli_commands/install.py
envdrift/cli_commands/partial.py
envdrift/cli_commands/sync.py
envdrift/cli_commands/validate.py
envdrift/cli_commands/vault.py
envdrift/cli_commands/version.py
envdrift/core/__init__.py
envdrift/core/diff.py
envdrift/core/encryption.py
envdrift/core/parser.py
envdrift/core/partial_encryption.py
envdrift/core/schema.py
envdrift/core/validator.py
envdrift/encryption/__init__.py
envdrift/encryption/base.py
envdrift/encryption/dotenvx.py
envdrift/encryption/sops.py
envdrift/integrations/__init__.py
envdrift/integrations/dotenvx.py
envdrift/integrations/hook_check.py
envdrift/integrations/precommit.py
envdrift/integrations/sops.py
envdrift/output/__init__.py
envdrift/output/rich.py
envdrift/scanner/__init__.py
envdrift/scanner/base.py
envdrift/scanner/detect_secrets.py
envdrift/scanner/engine.py
envdrift/scanner/git_secrets.py
envdrift/scanner/gitleaks.py
envdrift/scanner/ignores.py
envdrift/scanner/infisical.py
envdrift/scanner/kingfisher.py
envdrift/scanner/native.py
envdrift/scanner/output.py
envdrift/scanner/patterns.py
envdrift/scanner/platform_utils.py
envdrift/scanner/talisman.py
envdrift/scanner/trivy.py
envdrift/scanner/trufflehog.py
envdrift/sync/__init__.py
envdrift/sync/config.py
envdrift/sync/engine.py
envdrift/sync/operations.py
envdrift/sync/result.py
envdrift/utils/__init__.py
envdrift/utils/config.py
envdrift/utils/git.py
envdrift/vault/__init__.py
envdrift/vault/aws.py
envdrift/vault/azure.py
envdrift/vault/base.py
envdrift/vault/gcp.py
envdrift-10.7.0.dist-info/METADATA
envdrift-10.7.0.dist-info/WHEEL
envdrift-10.7.0.dist-info/entry_points.txt
envdrift-10.7.0.dist-info/licenses/LICENSE
envdrift-10.7.0.dist-info/RECORD
